ez_deploy.py
ez_deploy-1.0.4.dist-info/METADATA
ez_deploy-1.0.4.dist-info/WHEEL
ez_deploy-1.0.4.dist-info/entry_points.txt
ez_deploy-1.0.4.dist-info/top_level.txt
ez_deploy-1.0.4.dist-info/RECORD
