Metadata-Version: 2.1
Name: ez-deploy
Version: 1.0.4
Summary: Easy Deployment Tool
Home-page: https://github.com/koho/ez_deploy
Author: Gerhard Tan
Author-email: gerhard.gh.ta@gmail.com
License: UNKNOWN
Platform: any
Requires-Python: >=3.5
Requires-Dist: srvwrapper ; sys_platform == "win32"
